{
  "source": "www.pulsemindfulness.com",
  "pulled": "2026-07-12",
  "lines": [
    {"text": "Feel good in 10 sec, the wearable for presence.", "cat": "tagline", "where": "hero"},
    {"text": "Become Calm, Focused & Present", "cat": "tagline", "where": "hero"},
    {"text": "Pulse just might change your life.", "cat": "tagline", "where": "section heading"},
    {"text": "Snap out of autopilot and become present", "cat": "tagline", "where": "app features"},
    {"text": "Meditation apps de-invented", "cat": "tagline", "where": "app features"},
    {"text": "Shape new habits and focus", "cat": "tagline", "where": "app features"},
    {"text": "Be in your moment — not in your thoughts.", "cat": "tagline", "where": "tagline"},

    {"text": "Gentle vibrations on your finger remind you to pause, breathe, and reset — all day long.", "cat": "product", "where": "hero"},
    {"text": "To become calm and present, all you need is a 10-second micro-pause.", "cat": "product", "where": "how it works"},
    {"text": "Vibration — Snaps you out of autopilot.", "cat": "product", "where": "how it works"},
    {"text": "Practice — Gratitude exercise or deep breathing.", "cat": "product", "where": "how it works"},
    {"text": "No unnecessary screen time", "cat": "product", "where": "app features"},
    {"text": "Set your vibration patterns in the Pulse App, choose your intention, and let Pulse's gentle vibrations guide you throughout your day.", "cat": "product", "where": "app features"},
    {"text": "Mindfulness works, but we often forget to practice it. Pulse is here to change that forever.", "cat": "product", "where": "app features"},
    {"text": "Activate and Focus. Pulse discreetly starts vibrating every 30 seconds, every minute or every 5th minute.", "cat": "product", "where": "app features"},
    {"text": "For the first time ever, Pulse lets you enjoy a guided meditation without headphones.", "cat": "product", "where": "app features"},
    {"text": "A universe of the best teachers", "cat": "product", "where": "app features"},
    {"text": "The first smart wearable that doesn't stress you with data and information.", "cat": "product", "where": "USP"},
    {"text": "Mindfulness and wellbeing only", "cat": "product", "where": "USP"},
    {"text": "Pulse vibrations are completely separate from smartphone or other notifications.", "cat": "product", "where": "USP"},
    {"text": "Unintrusive and discreet", "cat": "product", "where": "USP"},
    {"text": "It's simply the most subtle smart wearable ever.", "cat": "product", "where": "USP"},
    {"text": "Smart without phone", "cat": "product", "where": "USP"},
    {"text": "Unlike regular meditation apps, it is made for digital detox.", "cat": "product", "where": "USP"},

    {"text": "Benefit — Scientifically proven: feel calm, feel present.", "cat": "benefits", "where": "how it works"},
    {"text": "Reduces stress and anxiety — by helping you snap out of autopilot and overthinking.", "cat": "benefits", "where": "benefits"},
    {"text": "Improves focus — by helping you form new habits and stopping you from getting sidetracked.", "cat": "benefits", "where": "benefits"},
    {"text": "Lets you be present — by keeping you in the moment without getting lost in thought.", "cat": "benefits", "where": "benefits"},
    {"text": "Calms you effortlessly — by making mindfulness and meditation a regular part of your life.", "cat": "benefits", "where": "benefits"},
    {"text": "After the vibration I returned to really being there with my son.", "cat": "benefits", "where": "testimonial"},
    {"text": "In the first week I noticed I stopped reaching for my phone during deep work.", "cat": "benefits", "where": "testimonial"},
    {"text": "Pulse helps me slow down, be present, and appreciate the moment I'm in.", "cat": "benefits", "where": "testimonial"},
    {"text": "It feels like the missing puzzle piece in my personal development journey.", "cat": "benefits", "where": "testimonial"},
    {"text": "Pulse has transformed the way I experience presence.", "cat": "benefits", "where": "testimonial"},
    {"text": "Pulse helps me feel more in control of my attention and my time.", "cat": "benefits", "where": "testimonial"},

    {"text": "SHOP NOW", "cat": "cta", "where": "CTA"},
    {"text": "SHOP", "cat": "cta", "where": "CTA"},
    {"text": "Unlock premium features", "cat": "cta", "where": "app features"},
    {"text": "Join a Community of Presence", "cat": "cta", "where": "testimonials"},
    {"text": "Stay in touch by subscribing to our newsletter!", "cat": "cta", "where": "newsletter"}
  ]
}
